{
  "timestamp": "2025-08-03T08:59:05.980Z",
  "project": "BC AI Ecosystem Phase 2 Expansion Import",
  "summary": {
    "totalCompanies": 100,
    "companiesImported": 54,
    "companiesSkipped": 46,
    "categoriesProcessed": 10,
    "errors": [],
    "importedCompanies": [
      "Dooly.ai",
      "Second Brain",
      "ExaThinkLabs",
      "Gumloop",
      "xTAO",
      "Ceedar",
      "Ideon Technologies",
      "Downtown.AI",
      "Molecular You",
      "Satisfai Health",
      "HEALWELL AI",
      "MedBright AI",
      "Light AI",
      "Quartech Systems",
      "Novatone Consulting",
      "Affinity Group",
      "Daric Clouding Solutions",
      "FireSwarm Solutions",
      "AIGreening",
      "SkyScout AI",
      "Arcus Power",
      "Styx Intelligence",
      "GeoComply",
      "GeoGuard",
      "Nebulock",
      "ZeroThreat",
      "CAFCyberCom",
      "CyberGuardians AI",
      "SafeVault",
      "IDVector",
      "Flow Blockchain",
      "LayeredLedger",
      "TokenFolio",
      "Vaultt AI",
      "Dragonscale",
      "LittleLit",
      "SpexCel Sensors",
      "NanoSense AI",
      "SenseHome",
      "EnviroDX",
      "Hydrolytics AI",
      "SkyLink Grid",
      "CircuitTree",
      "BeaconFleet",
      "HomeSight AI",
      "GSP Cloud",
      "Hypernatural",
      "Drag & Drop Law",
      "PicoPlan AI",
      "AutoPrompt",
      "CraftML",
      "StoryForge AI",
      "CortexQuill",
      "PromptPlayground"
    ],
    "skippedCompanies": [
      "Klue",
      "Penny AI",
      "Browse AI",
      "Swae",
      "SquareKnot Analytics",
      "LōD Technologies",
      "Picovoice",
      "VRFY Inc.",
      "VRIFY Technology",
      "Avicena AI",
      "1SecondPainting",
      "UnlockLand",
      "Binta Financial",
      "Artemis",
      "Apera AI",
      "Neupeak Robotics",
      "Plantiga",
      "EPIC Semiconductors",
      "Motion Metrics",
      "Wayve",
      "Implant Genius",
      "BujiBui",
      "Prenuvo",
      "SenseNet",
      "Spexi",
      "Veritree",
      "Kanooq Industries",
      "Sparkgeo",
      "Properti Edge",
      "Secur3D",
      "Felix Payment Systems",
      "Levr Technologies",
      "Akche",
      "Fintel Connect",
      "Quandri",
      "Cifra",
      "Lumen5",
      "FansNetwork",
      "Spheria",
      "XARIIA",
      "Flento",
      "Damon Tech",
      "Inverted AI",
      "PixelWizard Labs",
      "Plasmatic Technologies",
      "Caseway"
    ]
  },
  "importDetails": {
    "totalProcessed": 100,
    "successfulImports": 54,
    "skippedExisting": 46,
    "categoriesProcessed": 10,
    "errorCount": 0,
    "successRate": "54.0"
  },
  "phase2Achievement": {
    "previousTotal": 764,
    "newCompaniesAdded": 54,
    "projectedTotal": 818,
    "totalGrowth": "7.1%"
  },
  "importedCompanies": [
    "Dooly.ai",
    "Second Brain",
    "ExaThinkLabs",
    "Gumloop",
    "xTAO",
    "Ceedar",
    "Ideon Technologies",
    "Downtown.AI",
    "Molecular You",
    "Satisfai Health",
    "HEALWELL AI",
    "MedBright AI",
    "Light AI",
    "Quartech Systems",
    "Novatone Consulting",
    "Affinity Group",
    "Daric Clouding Solutions",
    "FireSwarm Solutions",
    "AIGreening",
    "SkyScout AI",
    "Arcus Power",
    "Styx Intelligence",
    "GeoComply",
    "GeoGuard",
    "Nebulock",
    "ZeroThreat",
    "CAFCyberCom",
    "CyberGuardians AI",
    "SafeVault",
    "IDVector",
    "Flow Blockchain",
    "LayeredLedger",
    "TokenFolio",
    "Vaultt AI",
    "Dragonscale",
    "LittleLit",
    "SpexCel Sensors",
    "NanoSense AI",
    "SenseHome",
    "EnviroDX",
    "Hydrolytics AI",
    "SkyLink Grid",
    "CircuitTree",
    "BeaconFleet",
    "HomeSight AI",
    "GSP Cloud",
    "Hypernatural",
    "Drag & Drop Law",
    "PicoPlan AI",
    "AutoPrompt",
    "CraftML",
    "StoryForge AI",
    "CortexQuill",
    "PromptPlayground"
  ],
  "skippedCompanies": [
    "Klue",
    "Penny AI",
    "Browse AI",
    "Swae",
    "SquareKnot Analytics",
    "LōD Technologies",
    "Picovoice",
    "VRFY Inc.",
    "VRIFY Technology",
    "Avicena AI",
    "1SecondPainting",
    "UnlockLand",
    "Binta Financial",
    "Artemis",
    "Apera AI",
    "Neupeak Robotics",
    "Plantiga",
    "EPIC Semiconductors",
    "Motion Metrics",
    "Wayve",
    "Implant Genius",
    "BujiBui",
    "Prenuvo",
    "SenseNet",
    "Spexi",
    "Veritree",
    "Kanooq Industries",
    "Sparkgeo",
    "Properti Edge",
    "Secur3D",
    "Felix Payment Systems",
    "Levr Technologies",
    "Akche",
    "Fintel Connect",
    "Quandri",
    "Cifra",
    "Lumen5",
    "FansNetwork",
    "Spheria",
    "XARIIA",
    "Flento",
    "Damon Tech",
    "Inverted AI",
    "PixelWizard Labs",
    "Plasmatic Technologies",
    "Caseway"
  ],
  "errors": []
}